[
  {
    "sNo": 1,
    "regalCode": "MA 01",
    "excellenceCode": "EX 25",
    "varnCode": "-",
    "rcCode": "-",
    "snalcoCode": "-",
    "genericName": "Big Rail Nut",
    "imageFilename": "MA-01.png",
    "codeSource": "Regal",
    "priority": 1,
    "allCodes": "MA 01 | EX 25"
  },
  {
    "sNo": 2,
    "regalCode": "MA 07",
    "excellenceCode": "-",
    "varnCode": "-",
    "rcCode": "-",
    "snalcoCode": "-",
    "genericName": "80mm Mini Rail",
    "imageFilename": "MA-07.png",
    "codeSource": "Regal",
    "priority": 1,
    "allCodes": "MA 07"
  },
  {
    "sNo": 3,
    "regalCode": "MA 09",
    "excellenceCode": "-",
    "varnCode": "-",
    "rcCode": "-",
    "snalcoCode": "-",
    "genericName": "Standing Seam Clamp - Part B (Type 1)",
    "imageFilename": "MA-09.png",
    "codeSource": "Regal",
    "priority": 1,
    "allCodes": "MA 09"
  },
  {
    "sNo": 4,
    "regalCode": "MA 10",
    "excellenceCode": "-",
    "varnCode": "-",
    "rcCode": "-",
    "snalcoCode": "-",
    "genericName": "Standing Seam Clamp - Part A (Type 1)",
    "imageFilename": "MA-10.png",
    "codeSource": "Regal",
    "priority": 1,
    "allCodes": "MA 10"
  },
  {
    "sNo": 5,
    "regalCode": "MA 11C",
    "excellenceCode": "-",
    "varnCode": "-",
    "rcCode": "-",
    "snalcoCode": "-",
    "genericName": "150mm Walkway Section",
    "imageFilename": "MA-11C.png",
    "codeSource": "Regal",
    "priority": 1,
    "allCodes": "MA 11C"
  },
  {
    "sNo": 6,
    "regalCode": "MA 12",
    "excellenceCode": "EX 30",
    "varnCode": "-",
    "rcCode": "-",
    "snalcoCode": "-",
    "genericName": "25mm Base Rail",
    "imageFilename": "MA-12.png",
    "codeSource": "Regal",
    "priority": 1,
    "allCodes": "MA 12 | EX 30"
  },
  {
    "sNo": 7,
    "regalCode": "MA 16",
    "excellenceCode": "-",
    "varnCode": "-",
    "rcCode": "-",
    "snalcoCode": "-",
    "genericName": "Mid Clamp - 25mm Module Gap",
    "imageFilename": "MA-16.png",
    "codeSource": "Regal",
    "priority": 1,
    "allCodes": "MA 16"
  },
  {
    "sNo": 8,
    "regalCode": "MA 17",
    "excellenceCode": "-",
    "varnCode": "SR 01",
    "rcCode": "-",
    "snalcoCode": "-",
    "genericName": "35mm End Clamp (Type 1)",
    "imageFilename": "MA-17.png",
    "codeSource": "Regal",
    "priority": 1,
    "allCodes": "MA 17 | SR 01"
  },
  {
    "sNo": 9,
    "regalCode": "MA 23",
    "excellenceCode": "-",
    "varnCode": "-",
    "rcCode": "-",
    "snalcoCode": "-",
    "genericName": "100mm Short Rail (In)",
    "imageFilename": "MA-23.png",
    "codeSource": "Regal",
    "priority": 1,
    "allCodes": "MA 23"
  },
  {
    "sNo": 10,
    "regalCode": "MA 24",
    "excellenceCode": "-",
    "varnCode": "-",
    "rcCode": "-",
    "snalcoCode": "-",
    "genericName": "40mm End Clamp (Type 1)",
    "imageFilename": "MA-24.png",
    "codeSource": "Regal",
    "priority": 1,
    "allCodes": "MA 24"
  },
  {
    "sNo": 11,
    "regalCode": "MA 25A",
    "excellenceCode": "EX 37",
    "varnCode": "-",
    "rcCode": "-",
    "snalcoCode": "-",
    "genericName": "V Rail (Type 2)",
    "imageFilename": "MA-25A.png",
    "codeSource": "Regal",
    "priority": 1,
    "allCodes": "MA 25A | EX 37"
  },
  {
    "sNo": 12,
    "regalCode": "MA 26",
    "excellenceCode": "-",
    "varnCode": "-",
    "rcCode": "-",
    "snalcoCode": "-",
    "genericName": "Standing Seam H Clamp (Type 1)",
    "imageFilename": "MA-26.png",
    "codeSource": "Regal",
    "priority": 1,
    "allCodes": "MA 26"
  },
  {
    "sNo": 13,
    "regalCode": "MA 27",
    "excellenceCode": "-",
    "varnCode": "SR 04",
    "rcCode": "SU 04",
    "snalcoCode": "-",
    "genericName": "65mm Short Rail (In)_V2",
    "imageFilename": "MA-27.png",
    "codeSource": "Regal",
    "priority": 1,
    "allCodes": "MA 27 | SR 04 | SU 04"
  },
  {
    "sNo": 14,
    "regalCode": "MA 28",
    "excellenceCode": "-",
    "varnCode": "-",
    "rcCode": "-",
    "snalcoCode": "-",
    "genericName": "21mm Strut Channel",
    "imageFilename": "MA-28.png",
    "codeSource": "Regal",
    "priority": 1,
    "allCodes": "MA 28"
  },
  {
    "sNo": 15,
    "regalCode": "MA 29",
    "excellenceCode": "EX 20",
    "varnCode": "-",
    "rcCode": "-",
    "snalcoCode": "-",
    "genericName": "Small Rail Nut",
    "imageFilename": "MA-29.png",
    "codeSource": "Regal",
    "priority": 1,
    "allCodes": "MA 29 | EX 20"
  },
  {
    "sNo": 16,
    "regalCode": "MA 30",
    "excellenceCode": "-",
    "varnCode": "-",
    "rcCode": "-",
    "snalcoCode": "-",
    "genericName": "Purlin Clamp",
    "imageFilename": "MA-30.png",
    "codeSource": "Regal",
    "priority": 1,
    "allCodes": "MA 30"
  },
  {
    "sNo": 17,
    "regalCode": "MA 31",
    "excellenceCode": "-",
    "varnCode": "-",
    "rcCode": "-",
    "snalcoCode": "-",
    "genericName": "75mm Short Rail (In)_V2",
    "imageFilename": "MA-31.png",
    "codeSource": "Regal",
    "priority": 1,
    "allCodes": "MA 31"
  },
  {
    "sNo": 18,
    "regalCode": "MA 34",
    "excellenceCode": "EX 58",
    "varnCode": "SR 10",
    "rcCode": "SR 01 (RC",
    "snalcoCode": "-",
    "genericName": "41mm Strut Channel",
    "imageFilename": "MA-34.png",
    "codeSource": "Regal",
    "priority": 1,
    "allCodes": "MA 34 | EX 58 | SR 10 | SR 01 (RC"
  },
  {
    "sNo": 19,
    "regalCode": "MA 35",
    "excellenceCode": "EX 55",
    "varnCode": "SR 02",
    "rcCode": "-",
    "snalcoCode": "-",
    "genericName": "Mid Clamp - 21mm Module Gap",
    "imageFilename": "MA-35.png",
    "codeSource": "Regal",
    "priority": 1,
    "allCodes": "MA 35 | EX 55 | SR 02 | RL 49703"
  },
  {
    "sNo": 20,
    "regalCode": "MA 36",
    "excellenceCode": "-",
    "varnCode": "-",
    "rcCode": "-",
    "snalcoCode": "-",
    "genericName": "9mm Circular Tube",
    "imageFilename": "MA-36.png",
    "codeSource": "Regal",
    "priority": 1,
    "allCodes": "MA 36"
  },
  {
    "sNo": 21,
    "regalCode": "MA 38",
    "excellenceCode": "EX 52",
    "varnCode": "-",
    "rcCode": "-",
    "snalcoCode": "-",
    "genericName": "Standing Seam H Clamp (Type 2)",
    "imageFilename": "MA-38.png",
    "codeSource": "Regal",
    "priority": 1,
    "allCodes": "MA 38 | EX 52"
  },
  {
    "sNo": 22,
    "regalCode": "MA 39",
    "excellenceCode": "EX 19",
    "varnCode": "-",
    "rcCode": "-",
    "snalcoCode": "-",
    "genericName": "75/25mm - 90 -  Mini Rail",
    "imageFilename": "MA-39.png",
    "codeSource": "Regal",
    "priority": 1,
    "allCodes": "MA 39 | EX 19"
  },
  {
    "sNo": 23,
    "regalCode": "MA 40",
    "excellenceCode": "EX 31",
    "varnCode": "SR 07",
    "rcCode": "SU 01",
    "snalcoCode": "-",
    "genericName": "70/27mm - 69 - Mini Rail",
    "imageFilename": "MA-40.png",
    "codeSource": "Regal",
    "priority": 1,
    "allCodes": "MA 40 | EX 31 | SR 07 | SU 01"
  },
  {
    "sNo": 24,
    "regalCode": "MA 41",
    "excellenceCode": "EX 22",
    "varnCode": "-",
    "rcCode": "-",
    "snalcoCode": "-",
    "genericName": "75/36mm - 90 - Mini Rail",
    "imageFilename": "MA-41.png",
    "codeSource": "Regal",
    "priority": 1,
    "allCodes": "MA 41 | EX 22"
  },
  {
    "sNo": 25,
    "regalCode": "MA 42",
    "excellenceCode": "-",
    "varnCode": "-",
    "rcCode": "-",
    "snalcoCode": "-",
    "genericName": "30mm End Clamp",
    "imageFilename": "MA-42.png",
    "codeSource": "Regal",
    "priority": 1,
    "allCodes": "MA 42"
  },
  {
    "sNo": 26,
    "regalCode": "MA 43",
    "excellenceCode": "EX 03",
    "varnCode": "SR 14",
    "rcCode": "SU 08",
    "snalcoCode": "-",
    "genericName": "40mm Long Rail",
    "imageFilename": "MA-43.png",
    "codeSource": "Regal",
    "priority": 1,
    "allCodes": "MA 43 | EX 03 | SR 14 | SU 08 | RL 49702 | SD 4328"
  },
  {
    "sNo": 27,
    "regalCode": "MA 44",
    "excellenceCode": "EX 15",
    "varnCode": "-",
    "rcCode": "-",
    "snalcoCode": "-",
    "genericName": "Inner U Cleat",
    "imageFilename": "MA-44.png",
    "codeSource": "Regal",
    "priority": 1,
    "allCodes": "MA 44 | EX 15"
  },
  {
    "sNo": 28,
    "regalCode": "MA 46",
    "excellenceCode": "EX 23",
    "varnCode": "-",
    "rcCode": "-",
    "snalcoCode": "-",
    "genericName": "Hook Rail Nut",
    "imageFilename": "MA-46.png",
    "codeSource": "Regal",
    "priority": 1,
    "allCodes": "MA 46 | EX 23"
  },
  {
    "sNo": 29,
    "regalCode": "MA 47",
    "excellenceCode": "-",
    "varnCode": "-",
    "rcCode": "-",
    "snalcoCode": "-",
    "genericName": "Mid Clamp (M+)",
    "imageFilename": "MA-47.png",
    "codeSource": "Regal",
    "priority": 1,
    "allCodes": "MA 47"
  },
  {
    "sNo": 30,
    "regalCode": "MA 48",
    "excellenceCode": "-",
    "varnCode": "-",
    "rcCode": "-",
    "snalcoCode": "-",
    "genericName": "Proflex - Standing Seam Clamp - Part A",
    "imageFilename": "MA-48.png",
    "codeSource": "Regal",
    "priority": 1,
    "allCodes": "MA 48"
  },
  {
    "sNo": 31,
    "regalCode": "MA 49",
    "excellenceCode": "-",
    "varnCode": "-",
    "rcCode": "-",
    "snalcoCode": "-",
    "genericName": "Proflex - Standing Seam Clamp - Part B",
    "imageFilename": "MA-49.png",
    "codeSource": "Regal",
    "priority": 1,
    "allCodes": "MA 49"
  },
  {
    "sNo": 32,
    "regalCode": "MA 50",
    "excellenceCode": "EX 07",
    "varnCode": "SR 05",
    "rcCode": "SU 07",
    "snalcoCode": "-",
    "genericName": "65mm Short Rail (Ex)",
    "imageFilename": "MA-50.png",
    "codeSource": "Regal",
    "priority": 1,
    "allCodes": "MA 50 | EX 07 | SR 05 | SU 07"
  },
  {
    "sNo": 33,
    "regalCode": "MA 51",
    "excellenceCode": "EX 32",
    "varnCode": "SR 06",
    "rcCode": "SU 06",
    "snalcoCode": "-",
    "genericName": "100mm Short Rail (Ex)",
    "imageFilename": "MA-51.png",
    "codeSource": "Regal",
    "priority": 1,
    "allCodes": "MA 51 | EX 32 | SR 06 | SU 06 | SD 4330"
  },
  {
    "sNo": 34,
    "regalCode": "MA 52",
    "excellenceCode": "EX 67",
    "varnCode": "-",
    "rcCode": "-",
    "snalcoCode": "-",
    "genericName": "Asbestos Curved Base",
    "imageFilename": "MA-52.png",
    "codeSource": "Regal",
    "priority": 1,
    "allCodes": "MA 52 | EX 67"
  },
  {
    "sNo": 35,
    "regalCode": "MA 54",
    "excellenceCode": "EX 21",
    "varnCode": "-",
    "rcCode": "-",
    "snalcoCode": "-",
    "genericName": "89mm L Cleat",
    "imageFilename": "MA-54.png",
    "codeSource": "Regal",
    "priority": 1,
    "allCodes": "MA 54 | EX 21"
  },
  {
    "sNo": 36,
    "regalCode": "MA 55",
    "excellenceCode": "-",
    "varnCode": "SR 08",
    "rcCode": "SU 05",
    "snalcoCode": "-",
    "genericName": "L Type Long Rail_V2",
    "imageFilename": "MA-55.png",
    "codeSource": "Regal",
    "priority": 1,
    "allCodes": "MA 55 | SR 08 | SU 05"
  },
  {
    "sNo": 37,
    "regalCode": "MA 56",
    "excellenceCode": "-",
    "varnCode": "-",
    "rcCode": "-",
    "snalcoCode": "-",
    "genericName": "70mm Short Rail (In)",
    "imageFilename": "MA-56.png",
    "codeSource": "Regal",
    "priority": 1,
    "allCodes": "MA 56"
  },
  {
    "sNo": 38,
    "regalCode": "MA 57",
    "excellenceCode": "EX 16",
    "varnCode": "-",
    "rcCode": "-",
    "snalcoCode": "-",
    "genericName": "Standing Seam Walkway Clamp 1",
    "imageFilename": "MA-57.png",
    "codeSource": "Regal",
    "priority": 1,
    "allCodes": "MA 57 | EX 16"
  },
  {
    "sNo": 39,
    "regalCode": "MA 58",
    "excellenceCode": "-",
    "varnCode": "-",
    "rcCode": "-",
    "snalcoCode": "-",
    "genericName": "Standing Seam Clamp - Part A (Type 2)",
    "imageFilename": "MA-58.png",
    "codeSource": "Regal",
    "priority": 1,
    "allCodes": "MA 58"
  },
  {
    "sNo": 40,
    "regalCode": "MA 59",
    "excellenceCode": "-",
    "varnCode": "-",
    "rcCode": "-",
    "snalcoCode": "-",
    "genericName": "Standing Seam Clamp - Part B (Type 2)",
    "imageFilename": "MA-59.png",
    "codeSource": "Regal",
    "priority": 1,
    "allCodes": "MA 59"
  },
  {
    "sNo": 41,
    "regalCode": "MA 60",
    "excellenceCode": "-",
    "varnCode": "-",
    "rcCode": "-",
    "snalcoCode": "-",
    "genericName": "FRP Walkway M Clamp",
    "imageFilename": "MA-60.png",
    "codeSource": "Regal",
    "priority": 1,
    "allCodes": "MA 60"
  },
  {
    "sNo": 42,
    "regalCode": "MA 63",
    "excellenceCode": "-",
    "varnCode": "-",
    "rcCode": "-",
    "snalcoCode": "-",
    "genericName": "Standing Seam Clamp (Type 3) (2x)",
    "imageFilename": "MA-63.png",
    "codeSource": "Regal",
    "priority": 1,
    "allCodes": "MA 63"
  },
  {
    "sNo": 43,
    "regalCode": "MA 64",
    "excellenceCode": "EX 34",
    "varnCode": "-",
    "rcCode": "-",
    "snalcoCode": "-",
    "genericName": "Kalzip Clamp - Part B",
    "imageFilename": "MA-64.png",
    "codeSource": "Regal",
    "priority": 1,
    "allCodes": "MA 64 | EX 34"
  },
  {
    "sNo": 44,
    "regalCode": "MA 65",
    "excellenceCode": "EX 33",
    "varnCode": "-",
    "rcCode": "-",
    "snalcoCode": "-",
    "genericName": "Kalzip Clamp - Part A",
    "imageFilename": "MA-65.png",
    "codeSource": "Regal",
    "priority": 1,
    "allCodes": "MA 65 | EX 33"
  },
  {
    "sNo": 45,
    "regalCode": "MA 68",
    "excellenceCode": "-",
    "varnCode": "-",
    "rcCode": "-",
    "snalcoCode": "-",
    "genericName": "Hat Base",
    "imageFilename": "MA-68.png",
    "codeSource": "Regal",
    "priority": 1,
    "allCodes": "MA 68"
  },
  {
    "sNo": 46,
    "regalCode": "MA 69",
    "excellenceCode": "EX 62",
    "varnCode": "-",
    "rcCode": "-",
    "snalcoCode": "-",
    "genericName": "Rectangle Column",
    "imageFilename": "MA-69.png",
    "codeSource": "Regal",
    "priority": 1,
    "allCodes": "MA 69 | EX 62"
  },
  {
    "sNo": 47,
    "regalCode": "MA 72",
    "excellenceCode": "EX 24",
    "varnCode": "-",
    "rcCode": "-",
    "snalcoCode": "-",
    "genericName": "External Long Rail Jointer",
    "imageFilename": "MA-72.png",
    "codeSource": "Regal",
    "priority": 1,
    "allCodes": "MA 72 | EX 24 | RL 49705"
  },
  {
    "sNo": 48,
    "regalCode": "MA 73",
    "excellenceCode": "EX 68",
    "varnCode": "-",
    "rcCode": "-",
    "snalcoCode": "-",
    "genericName": "Round Tube Bracket",
    "imageFilename": "MA-73.png",
    "codeSource": "Regal",
    "priority": 1,
    "allCodes": "MA 73 | EX 68"
  },
  {
    "sNo": 49,
    "regalCode": "MA 74",
    "excellenceCode": "EX 63",
    "varnCode": "-",
    "rcCode": "-",
    "snalcoCode": "-",
    "genericName": "Hand Rail Tube",
    "imageFilename": "MA-74.png",
    "codeSource": "Regal",
    "priority": 1,
    "allCodes": "MA 74 | EX 63"
  },
  {
    "sNo": 50,
    "regalCode": "MA 75",
    "excellenceCode": "EX 28",
    "varnCode": "-",
    "rcCode": "-",
    "snalcoCode": "-",
    "genericName": "FRP Walkway M Clamp_V2",
    "imageFilename": "MA-75.png",
    "codeSource": "Regal",
    "priority": 1,
    "allCodes": "MA 75 | EX 28"
  },
  {
    "sNo": 51,
    "regalCode": "MA 76",
    "excellenceCode": "EX 09",
    "varnCode": "-",
    "rcCode": "-",
    "snalcoCode": "-",
    "genericName": "L Type Long Rail_V3",
    "imageFilename": "MA-76.png",
    "codeSource": "Regal",
    "priority": 1,
    "allCodes": "MA 76 | EX 09"
  },
  {
    "sNo": 52,
    "regalCode": "MA 77",
    "excellenceCode": "-",
    "varnCode": "-",
    "rcCode": "-",
    "snalcoCode": "-",
    "genericName": "Standing Seam Clamp - Part B (Type 4)",
    "imageFilename": "MA-77.png",
    "codeSource": "Regal",
    "priority": 1,
    "allCodes": "MA 77"
  },
  {
    "sNo": 53,
    "regalCode": "MA 81",
    "excellenceCode": "-",
    "varnCode": "-",
    "rcCode": "-",
    "snalcoCode": "-",
    "genericName": "75mm Standing Seam Clamp - External",
    "imageFilename": "MA-81.png",
    "codeSource": "Regal",
    "priority": 1,
    "allCodes": "MA 81"
  },
  {
    "sNo": 54,
    "regalCode": "MA 82",
    "excellenceCode": "-",
    "varnCode": "-",
    "rcCode": "-",
    "snalcoCode": "-",
    "genericName": "65/17mm - 74 - Mini Rail (Ex)",
    "imageFilename": "MA-82.png",
    "codeSource": "Regal",
    "priority": 1,
    "allCodes": "MA 82"
  },
  {
    "sNo": 55,
    "regalCode": "LA25x25",
    "excellenceCode": "EX 64",
    "varnCode": "-",
    "rcCode": "-",
    "snalcoCode": "-",
    "genericName": "L Angle - 25x25mm",
    "imageFilename": "LA25x25.png",
    "codeSource": "Regal",
    "priority": 1,
    "allCodes": "LA25x25 | EX 64"
  },
  {
    "sNo": 56,
    "regalCode": "-",
    "excellenceCode": "-",
    "varnCode": "SR 03",
    "rcCode": "SU 12",
    "snalcoCode": "-",
    "genericName": "35mm End Clamp (Type 2)",
    "imageFilename": "SR-03.png",
    "codeSource": "VARN",
    "priority": 3,
    "allCodes": "SR 03 | SU 12"
  },
  {
    "sNo": 57,
    "regalCode": "MA 107",
    "excellenceCode": "EX 61",
    "varnCode": "SR 09",
    "rcCode": "SU 03",
    "snalcoCode": "-",
    "genericName": "L Angle - 45x35mm",
    "imageFilename": "MA-107.png",
    "codeSource": "Regal",
    "priority": 1,
    "allCodes": "MA 107 | EX 61 | SR 09 | SU 03"
  },
  {
    "sNo": 58,
    "regalCode": "-",
    "excellenceCode": "-",
    "varnCode": "SR 11",
    "rcCode": "SU 14",
    "snalcoCode": "-",
    "genericName": "70/42mm Mini Rail",
    "imageFilename": "SR-11.png",
    "codeSource": "VARN",
    "priority": 3,
    "allCodes": "SR 11 | SU 14"
  },
  {
    "sNo": 59,
    "regalCode": "-",
    "excellenceCode": "EX 60",
    "varnCode": "SR 12",
    "rcCode": "-",
    "snalcoCode": "-",
    "genericName": "Round Tube Jointer",
    "imageFilename": "EX-60.png",
    "codeSource": "Excellence",
    "priority": 2,
    "allCodes": "EX 60 | SR 12"
  },
  {
    "sNo": 60,
    "regalCode": "-",
    "excellenceCode": "EX 54",
    "varnCode": "SR 13",
    "rcCode": "SU 11",
    "snalcoCode": "-",
    "genericName": "40mm End Clamp (Type 2)",
    "imageFilename": "EX-54.png",
    "codeSource": "Excellence",
    "priority": 2,
    "allCodes": "EX 54 | SR 13 | SU 11"
  },
  {
    "sNo": 61,
    "regalCode": "-",
    "excellenceCode": "-",
    "varnCode": "-",
    "rcCode": "SU 02",
    "snalcoCode": "-",
    "genericName": "35mm End Clamp (M+)",
    "imageFilename": "SU-02.png",
    "codeSource": "RC",
    "priority": 4,
    "allCodes": "SU 02"
  },
  {
    "sNo": 62,
    "regalCode": "-",
    "excellenceCode": "-",
    "varnCode": "-",
    "rcCode": "-",
    "snalcoCode": "-",
    "genericName": "175mm Walkway Section (2x)",
    "imageFilename": "DR-1.png",
    "codeSource": "Darshan",
    "priority": 6,
    "allCodes": "DR 1"
  },
  {
    "sNo": 63,
    "regalCode": "-",
    "excellenceCode": "-",
    "varnCode": "-",
    "rcCode": "-",
    "snalcoCode": "-",
    "genericName": "Ballast Tray Clamp",
    "imageFilename": "DR-2.png",
    "codeSource": "Darshan",
    "priority": 6,
    "allCodes": "DR 2 | RL 49706"
  },
  {
    "sNo": 64,
    "regalCode": "-",
    "excellenceCode": "-",
    "varnCode": "-",
    "rcCode": "-",
    "snalcoCode": "SN 5303",
    "genericName": "97/36mm - 90 - Mini Rail (Ex)",
    "imageFilename": "SN-5303.png",
    "codeSource": "SNALCO",
    "priority": 5,
    "allCodes": "SN 5303"
  },
  {
    "sNo": 65,
    "regalCode": "-",
    "excellenceCode": "-",
    "varnCode": "SR 16",
    "rcCode": "SU 13",
    "snalcoCode": "-",
    "genericName": "33mm End Clamp",
    "imageFilename": "SR-16.png",
    "codeSource": "VARN",
    "priority": 3,
    "allCodes": "SR 16 | SU 13"
  },
  {
    "sNo": 66,
    "regalCode": "MA 84",
    "excellenceCode": "EX 29",
    "varnCode": "-",
    "rcCode": "-",
    "snalcoCode": "-",
    "genericName": "FRP C Clamp",
    "imageFilename": "MA-84.png",
    "codeSource": "Regal",
    "priority": 1,
    "allCodes": "MA 84 | EX 29"
  },
  {
    "sNo": 67,
    "regalCode": "MA 85",
    "excellenceCode": "EX 49",
    "varnCode": "-",
    "rcCode": "-",
    "snalcoCode": "-",
    "genericName": "Kliplock 700 Clamp - Part B",
    "imageFilename": "MA-85.png",
    "codeSource": "Regal",
    "priority": 1,
    "allCodes": "MA 85 | EX 49"
  },
  {
    "sNo": 68,
    "regalCode": "MA 86",
    "excellenceCode": "EX 65",
    "varnCode": "-",
    "rcCode": "-",
    "snalcoCode": "-",
    "genericName": "Kliplock 700 Clamp - Part A",
    "imageFilename": "MA-86.png",
    "codeSource": "Regal",
    "priority": 1,
    "allCodes": "MA 86 | EX 65"
  },
  {
    "sNo": 69,
    "regalCode": "MA 87",
    "excellenceCode": "-",
    "varnCode": "-",
    "rcCode": "-",
    "snalcoCode": "-",
    "genericName": "Whistle Clamp",
    "imageFilename": "MA-87.png",
    "codeSource": "Regal",
    "priority": 1,
    "allCodes": "MA 87"
  },
  {
    "sNo": 70,
    "regalCode": "-",
    "excellenceCode": "EX 01",
    "varnCode": "-",
    "rcCode": "-",
    "snalcoCode": "-",
    "genericName": "CNT - Front Leg",
    "imageFilename": "EX-01.png",
    "codeSource": "Excellence",
    "priority": 2,
    "allCodes": "EX 01"
  },
  {
    "sNo": 71,
    "regalCode": "-",
    "excellenceCode": "EX 02",
    "varnCode": "-",
    "rcCode": "-",
    "snalcoCode": "-",
    "genericName": "CNT - Back Leg",
    "imageFilename": "EX-02.png",
    "codeSource": "Excellence",
    "priority": 2,
    "allCodes": "EX 02"
  },
  {
    "sNo": 72,
    "regalCode": "MA 112",
    "excellenceCode": "EX 04",
    "varnCode": "-",
    "rcCode": "-",
    "snalcoCode": "-",
    "genericName": "Mid Clamp (T4)",
    "imageFilename": "MA-112.png",
    "codeSource": "Regal",
    "priority": 1,
    "allCodes": "MA 112 | EX 04"
  },
  {
    "sNo": 73,
    "regalCode": "MA 111",
    "excellenceCode": "EX 05",
    "varnCode": "-",
    "rcCode": "-",
    "snalcoCode": "-",
    "genericName": "35mm End Clamp (T4)",
    "imageFilename": "MA-111.png",
    "codeSource": "Regal",
    "priority": 1,
    "allCodes": "MA 111 | EX 05"
  },
  {
    "sNo": 74,
    "regalCode": "MA 108",
    "excellenceCode": "EX 06",
    "varnCode": "-",
    "rcCode": "-",
    "snalcoCode": "-",
    "genericName": "80mm Short Rail(Ex)",
    "imageFilename": "MA-108.png",
    "codeSource": "Regal",
    "priority": 1,
    "allCodes": "MA 108 | EX 06"
  },
  {
    "sNo": 75,
    "regalCode": "MA 89",
    "excellenceCode": "EX 35",
    "varnCode": "-",
    "rcCode": "-",
    "snalcoCode": "-",
    "genericName": "Kalzip Flat Top Clamp",
    "imageFilename": "MA-89.png",
    "codeSource": "Regal",
    "priority": 1,
    "allCodes": "MA 89 | EX 35"
  },
  {
    "sNo": 76,
    "regalCode": "MA 90",
    "excellenceCode": "-",
    "varnCode": "-",
    "rcCode": "-",
    "snalcoCode": "-",
    "genericName": "L Type Long Rail - 60mm",
    "imageFilename": "MA-90.png",
    "codeSource": "Regal",
    "priority": 1,
    "allCodes": "MA 90"
  },
  {
    "sNo": 77,
    "regalCode": "MA 91",
    "excellenceCode": "EX 13",
    "varnCode": "-",
    "rcCode": "-",
    "snalcoCode": "-",
    "genericName": "Outer U Cleat - 82mm",
    "imageFilename": "MA-91.png",
    "codeSource": "Regal",
    "priority": 1,
    "allCodes": "MA 91 | EX 13"
  },
  {
    "sNo": 78,
    "regalCode": "MA 92",
    "excellenceCode": "-",
    "varnCode": "-",
    "rcCode": "-",
    "snalcoCode": "-",
    "genericName": "Tata Short Rail",
    "imageFilename": "MA-92.png",
    "codeSource": "Regal",
    "priority": 1,
    "allCodes": "MA 92"
  },
  {
    "sNo": 79,
    "regalCode": "MA 93",
    "excellenceCode": "-",
    "varnCode": "-",
    "rcCode": "-",
    "snalcoCode": "-",
    "genericName": "Tata Universal Module Clamp",
    "imageFilename": "MA-93.png",
    "codeSource": "Regal",
    "priority": 1,
    "allCodes": "MA 93"
  },
  {
    "sNo": 80,
    "regalCode": "MA 94",
    "excellenceCode": "-",
    "varnCode": "-",
    "rcCode": "-",
    "snalcoCode": "-",
    "genericName": "Tata Rail Nut",
    "imageFilename": "MA-94.png",
    "codeSource": "Regal",
    "priority": 1,
    "allCodes": "MA 94"
  },
  {
    "sNo": 81,
    "regalCode": "MA 95",
    "excellenceCode": "EX 47",
    "varnCode": "-",
    "rcCode": "-",
    "snalcoCode": "-",
    "genericName": "Multilock Seam Clamp - Part B",
    "imageFilename": "MA-95.png",
    "codeSource": "Regal",
    "priority": 1,
    "allCodes": "MA 95 | EX 47"
  },
  {
    "sNo": 82,
    "regalCode": "MA 97",
    "excellenceCode": "-",
    "varnCode": "-",
    "rcCode": "-",
    "snalcoCode": "-",
    "genericName": "Multilock Seam Clamp - Part A",
    "imageFilename": "MA-97.png",
    "codeSource": "Regal",
    "priority": 1,
    "allCodes": "MA 97"
  },
  {
    "sNo": 83,
    "regalCode": "MA 98",
    "excellenceCode": "EX 46",
    "varnCode": "-",
    "rcCode": "-",
    "snalcoCode": "-",
    "genericName": "L Type Long Rail Jointert_V2",
    "imageFilename": "MA-98.png",
    "codeSource": "Regal",
    "priority": 1,
    "allCodes": "MA 98 | EX 46"
  },
  {
    "sNo": 84,
    "regalCode": "MA 99",
    "excellenceCode": "EX 57",
    "varnCode": "-",
    "rcCode": "-",
    "snalcoCode": "-",
    "genericName": "Standing Seam Clamp - 100mm",
    "imageFilename": "MA-99.png",
    "codeSource": "Regal",
    "priority": 1,
    "allCodes": "MA 99 | EX 57"
  },
  {
    "sNo": 85,
    "regalCode": "MA 100",
    "excellenceCode": "-",
    "varnCode": "-",
    "rcCode": "SU 19",
    "snalcoCode": "-",
    "genericName": "External Long Rail_60mm",
    "imageFilename": "MA-100.png",
    "codeSource": "Regal",
    "priority": 1,
    "allCodes": "MA 100 | SU 19 | RL 49707"
  },
  {
    "sNo": 86,
    "regalCode": "MA 102",
    "excellenceCode": "-",
    "varnCode": "-",
    "rcCode": "-",
    "snalcoCode": "-",
    "genericName": "External 60mm Long Rail Jointer",
    "imageFilename": "MA-102.png",
    "codeSource": "Regal",
    "priority": 1,
    "allCodes": "MA 102"
  },
  {
    "sNo": 87,
    "regalCode": "-",
    "excellenceCode": "EX 08",
    "varnCode": "-",
    "rcCode": "-",
    "snalcoCode": "-",
    "genericName": "CNT - Face Leg",
    "imageFilename": "EX-08.png",
    "codeSource": "Excellence",
    "priority": 2,
    "allCodes": "EX 08"
  },
  {
    "sNo": 88,
    "regalCode": "-",
    "excellenceCode": "EX 10",
    "varnCode": "-",
    "rcCode": "SU 18",
    "snalcoCode": "-",
    "genericName": "98/27 - 75 - Mini Rail (Ex)",
    "imageFilename": "EX-10.png",
    "codeSource": "Excellence",
    "priority": 2,
    "allCodes": "EX 10 | SU 18"
  },
  {
    "sNo": 89,
    "regalCode": "-",
    "excellenceCode": "EX 11",
    "varnCode": "-",
    "rcCode": "SU 17",
    "snalcoCode": "-",
    "genericName": "98/27 - 69 - Mini Rail (Ex)",
    "imageFilename": "EX-11.png",
    "codeSource": "Excellence",
    "priority": 2,
    "allCodes": "EX 11 | SU 17"
  },
  {
    "sNo": 90,
    "regalCode": "-",
    "excellenceCode": "EX 12",
    "varnCode": "-",
    "rcCode": "SU 18",
    "snalcoCode": "-",
    "genericName": "98/29 - 73 - Mini Rail (Ex)",
    "imageFilename": "EX-12.png",
    "codeSource": "Excellence",
    "priority": 2,
    "allCodes": "EX 12 | SU 18"
  },
  {
    "sNo": 91,
    "regalCode": "-",
    "excellenceCode": "EX 17",
    "varnCode": "-",
    "rcCode": "-",
    "snalcoCode": "-",
    "genericName": "Emmvee Long Rail",
    "imageFilename": "EX-17.png",
    "codeSource": "Excellence",
    "priority": 2,
    "allCodes": "EX 17"
  },
  {
    "sNo": 92,
    "regalCode": "-",
    "excellenceCode": "EX 18",
    "varnCode": "-",
    "rcCode": "-",
    "snalcoCode": "-",
    "genericName": "Araymond Strut Rail - 73mm",
    "imageFilename": "EX-18.png",
    "codeSource": "Excellence",
    "priority": 2,
    "allCodes": "EX 18"
  },
  {
    "sNo": 93,
    "regalCode": "-",
    "excellenceCode": "EX 26",
    "varnCode": "-",
    "rcCode": "-",
    "snalcoCode": "-",
    "genericName": "100mm Short Rail (AR)",
    "imageFilename": "EX-26.png",
    "codeSource": "Excellence",
    "priority": 2,
    "allCodes": "EX 26 | RL 49701"
  },
  {
    "sNo": 94,
    "regalCode": "-",
    "excellenceCode": "-",
    "varnCode": "-",
    "rcCode": "-",
    "snalcoCode": "SN 5306",
    "genericName": "UX Long Rail - Large U Base",
    "imageFilename": "SN-5306.png",
    "codeSource": "SNALCO",
    "priority": 5,
    "allCodes": "SN 5306"
  },
  {
    "sNo": 95,
    "regalCode": "MA 103",
    "excellenceCode": "-",
    "varnCode": "-",
    "rcCode": "SU 20",
    "snalcoCode": "-",
    "genericName": "25mm Base Rail W/O Flange",
    "imageFilename": "MA-103.png",
    "codeSource": "Regal",
    "priority": 1,
    "allCodes": "MA 103 | SU 20"
  },
  {
    "sNo": 96,
    "regalCode": "MA 104",
    "excellenceCode": "-",
    "varnCode": "-",
    "rcCode": "-",
    "snalcoCode": "-",
    "genericName": "Multilok Flat Top Seam Clamp - Part A",
    "imageFilename": "MA-104.png",
    "codeSource": "Regal",
    "priority": 1,
    "allCodes": "MA 104"
  },
  {
    "sNo": 97,
    "regalCode": "MA 105",
    "excellenceCode": "EX 38",
    "varnCode": "-",
    "rcCode": "-",
    "snalcoCode": "-",
    "genericName": "H Bracket_V2",
    "imageFilename": "MA-105.png",
    "codeSource": "Regal",
    "priority": 1,
    "allCodes": "MA 105 | EX 38"
  },
  {
    "sNo": 98,
    "regalCode": "MA 106",
    "excellenceCode": "EX 50",
    "varnCode": "-",
    "rcCode": "-",
    "snalcoCode": "-",
    "genericName": "Kliplock 700 Flat Top Clamp - Part A",
    "imageFilename": "MA-106.png",
    "codeSource": "Regal",
    "priority": 1,
    "allCodes": "MA 106 | EX 50"
  },
  {
    "sNo": 99,
    "regalCode": "MA 109",
    "excellenceCode": "EX 53",
    "varnCode": "-",
    "rcCode": "-",
    "snalcoCode": "-",
    "genericName": "30mm End Clamp_V2",
    "imageFilename": "MA-109.png",
    "codeSource": "Regal",
    "priority": 1,
    "allCodes": "MA 109 | EX 53"
  },
  {
    "sNo": 100,
    "regalCode": "MA 110",
    "excellenceCode": "EX 39",
    "varnCode": "-",
    "rcCode": "SU 16",
    "snalcoCode": "-",
    "genericName": "Unified U Cleat",
    "imageFilename": "MA-110.png",
    "codeSource": "Regal",
    "priority": 1,
    "allCodes": "MA 110 | EX 39 | SU 16 | SD 4329"
  },
  {
    "sNo": 101,
    "regalCode": "-",
    "excellenceCode": "-",
    "varnCode": "-",
    "rcCode": "-",
    "snalcoCode": "SN 5307",
    "genericName": "Height Extender - U Long Rail",
    "imageFilename": "SN-5307.png",
    "codeSource": "SNALCO",
    "priority": 5,
    "allCodes": "SN 5307"
  },
  {
    "sNo": 102,
    "regalCode": "MA 113",
    "excellenceCode": "-",
    "varnCode": "-",
    "rcCode": "-",
    "snalcoCode": "-",
    "genericName": "Bitumen Rail Splice",
    "imageFilename": "MA-113.png",
    "codeSource": "Regal",
    "priority": 1,
    "allCodes": "MA 113"
  },
  {
    "sNo": 103,
    "regalCode": "MA 114",
    "excellenceCode": "EX 42",
    "varnCode": "-",
    "rcCode": "-",
    "snalcoCode": "-",
    "genericName": "RCC EW Channel (Purlin)",
    "imageFilename": "MA-114.png",
    "codeSource": "Regal",
    "priority": 1,
    "allCodes": "MA 114 | EX 42"
  },
  {
    "sNo": 104,
    "regalCode": "MA 115",
    "excellenceCode": "EX 45",
    "varnCode": "-",
    "rcCode": "-",
    "snalcoCode": "-",
    "genericName": "RCC Column 40X60",
    "imageFilename": "MA-115.png",
    "codeSource": "Regal",
    "priority": 1,
    "allCodes": "MA 115 | EX 45"
  },
  {
    "sNo": 105,
    "regalCode": "MA 116",
    "excellenceCode": "EX 44",
    "varnCode": "-",
    "rcCode": "-",
    "snalcoCode": "-",
    "genericName": "RCC Bracing 40X40",
    "imageFilename": "MA-116.png",
    "codeSource": "Regal",
    "priority": 1,
    "allCodes": "MA 116 | EX 44"
  },
  {
    "sNo": 106,
    "regalCode": "MA 117",
    "excellenceCode": "EX 43",
    "varnCode": "-",
    "rcCode": "-",
    "snalcoCode": "-",
    "genericName": "H Bracket-V3",
    "imageFilename": "MA-117.png",
    "codeSource": "Regal",
    "priority": 1,
    "allCodes": "MA 117 | EX 43"
  },
  {
    "sNo": 107,
    "regalCode": "MA 118",
    "excellenceCode": "EX 40",
    "varnCode": "-",
    "rcCode": "-",
    "snalcoCode": "-",
    "genericName": "RCC EW Splice (Purlin splcie)",
    "imageFilename": "MA-118.png",
    "codeSource": "Regal",
    "priority": 1,
    "allCodes": "MA 118 | EX 40"
  },
  {
    "sNo": 108,
    "regalCode": "MA 119",
    "excellenceCode": "EX 59",
    "varnCode": "-",
    "rcCode": "-",
    "snalcoCode": "-",
    "genericName": "RCC NS CHANNEL (Rafter)",
    "imageFilename": "MA-119.png",
    "codeSource": "Regal",
    "priority": 1,
    "allCodes": "MA 119 | EX 59"
  },
  {
    "sNo": 109,
    "regalCode": "MA 120",
    "excellenceCode": "-",
    "varnCode": "-",
    "rcCode": "-",
    "snalcoCode": "-",
    "genericName": "100 - 27- Mono Rail (Ex)",
    "imageFilename": "MA-120.png",
    "codeSource": "Regal",
    "priority": 1,
    "allCodes": "MA 120"
  },
  {
    "sNo": 110,
    "regalCode": "MA 121",
    "excellenceCode": "-",
    "varnCode": "-",
    "rcCode": "-",
    "snalcoCode": "-",
    "genericName": "30mm End Clamp_Type 2",
    "imageFilename": "MA-121.png",
    "codeSource": "Regal",
    "priority": 1,
    "allCodes": "MA 121"
  },
  {
    "sNo": 111,
    "regalCode": "MA 122",
    "excellenceCode": "-",
    "varnCode": "-",
    "rcCode": "-",
    "snalcoCode": "-",
    "genericName": "Mid Clamp - 27mm Module Gap",
    "imageFilename": "MA-122.png",
    "codeSource": "Regal",
    "priority": 1,
    "allCodes": "MA 122"
  },
  {
    "sNo": 112,
    "regalCode": "MA 123",
    "excellenceCode": "-",
    "varnCode": "-",
    "rcCode": "-",
    "snalcoCode": "-",
    "genericName": "M8 Spacer",
    "imageFilename": "MA-123.png",
    "codeSource": "Regal",
    "priority": 1,
    "allCodes": "MA 123"
  },
  {
    "sNo": 113,
    "regalCode": "-",
    "excellenceCode": "EX 36",
    "varnCode": "-",
    "rcCode": "-",
    "snalcoCode": "SN 5315",
    "genericName": "98/23 - 29 - Mini Rail (Ex)",
    "imageFilename": "EX-36.png",
    "codeSource": "Excellence",
    "priority": 2,
    "allCodes": "EX 36 | SN 5315"
  },
  {
    "sNo": 114,
    "regalCode": "-",
    "excellenceCode": "EX 41",
    "varnCode": "-",
    "rcCode": "-",
    "snalcoCode": "-",
    "genericName": "Flat Base (Type 2)",
    "imageFilename": "EX-41.png",
    "codeSource": "Excellence",
    "priority": 2,
    "allCodes": "EX 41"
  },
  {
    "sNo": 115,
    "regalCode": "-",
    "excellenceCode": "-",
    "varnCode": "SR 18",
    "rcCode": "-",
    "snalcoCode": "-",
    "genericName": "Purlin Clamp (Type 2)",
    "imageFilename": "SR-18.png",
    "codeSource": "VARN",
    "priority": 3,
    "allCodes": "SR 18"
  },
  {
    "sNo": 116,
    "regalCode": "-",
    "excellenceCode": "-",
    "varnCode": "SR 17",
    "rcCode": "-",
    "snalcoCode": "-",
    "genericName": "Teeth Washer",
    "imageFilename": "SR-17.png",
    "codeSource": "VARN",
    "priority": 3,
    "allCodes": "SR 17"
  },
  {
    "sNo": 117,
    "regalCode": "-",
    "excellenceCode": "-",
    "varnCode": "-",
    "rcCode": "-",
    "snalcoCode": "SN 5311",
    "genericName": "Bitumen Rail - 100mm",
    "imageFilename": "SN-5311.png",
    "codeSource": "SNALCO",
    "priority": 5,
    "allCodes": "SN 5311"
  },
  {
    "sNo": 118,
    "regalCode": "-",
    "excellenceCode": "-",
    "varnCode": "-",
    "rcCode": "-",
    "snalcoCode": "SN 5312",
    "genericName": "100/35 - 105 - Mini Rail (Ex)",
    "imageFilename": "SN-5312.png",
    "codeSource": "SNALCO",
    "priority": 5,
    "allCodes": "SN 5312"
  },
  {
    "sNo": 119,
    "regalCode": "-",
    "excellenceCode": "-",
    "varnCode": "SR 15",
    "rcCode": "SU 15",
    "snalcoCode": "-",
    "genericName": "Standing Seam Clamp - 65mm",
    "imageFilename": "SR-15.png",
    "codeSource": "VARN",
    "priority": 3,
    "allCodes": "SR 15 | SU 15"
  },
  {
    "sNo": 120,
    "regalCode": "-",
    "excellenceCode": "EX 51",
    "varnCode": "-",
    "rcCode": "-",
    "snalcoCode": "-",
    "genericName": "Toe Guard",
    "imageFilename": "EX-51.png",
    "codeSource": "Excellence",
    "priority": 2,
    "allCodes": "EX 51"
  },
  {
    "sNo": 121,
    "regalCode": "MA 124",
    "excellenceCode": "-",
    "varnCode": "-",
    "rcCode": "-",
    "snalcoCode": "-",
    "genericName": "Waaree Flexible Module Bracket",
    "imageFilename": "MA-124.png",
    "codeSource": "Regal",
    "priority": 1,
    "allCodes": "MA 124"
  },
  {
    "sNo": 122,
    "regalCode": "MA 125",
    "excellenceCode": "EX 66",
    "varnCode": "-",
    "rcCode": "-",
    "snalcoCode": "-",
    "genericName": "U Bracket",
    "imageFilename": "MA-125.png",
    "codeSource": "Regal",
    "priority": 1,
    "allCodes": "MA 125 | EX 66"
  },
  {
    "sNo": 123,
    "regalCode": "MA 126",
    "excellenceCode": "-",
    "varnCode": "-",
    "rcCode": "-",
    "snalcoCode": "-",
    "genericName": "Module Flange Bracket",
    "imageFilename": "MA-126.png",
    "codeSource": "Regal",
    "priority": 1,
    "allCodes": "MA 126"
  },
  {
    "sNo": 124,
    "regalCode": "MA 127",
    "excellenceCode": "-",
    "varnCode": "-",
    "rcCode": "-",
    "snalcoCode": "-",
    "genericName": "Sunrack Bottom Clamp",
    "imageFilename": "MA-127.png",
    "codeSource": "Regal",
    "priority": 1,
    "allCodes": "MA 127"
  },
  {
    "sNo": 125,
    "regalCode": "-",
    "excellenceCode": "EX 56",
    "varnCode": "-",
    "rcCode": "-",
    "snalcoCode": "-",
    "genericName": "117mm L Cleat",
    "imageFilename": "EX-56.png",
    "codeSource": "Excellence",
    "priority": 2,
    "allCodes": "EX 56"
  },
  {
    "sNo": 126,
    "regalCode": "-",
    "excellenceCode": "-",
    "varnCode": "-",
    "rcCode": "SU 09",
    "snalcoCode": "-",
    "genericName": "60mm T Bolt Short Rail",
    "imageFilename": "SU-09.png",
    "codeSource": "RC",
    "priority": 4,
    "allCodes": "SU 09"
  },
  {
    "sNo": 127,
    "regalCode": "-",
    "excellenceCode": "-",
    "varnCode": "-",
    "rcCode": "SU 10",
    "snalcoCode": "-",
    "genericName": "Mid Clamp - 15mm Module Gap",
    "imageFilename": "SU-10.png",
    "codeSource": "RC",
    "priority": 4,
    "allCodes": "SU 10"
  },
  {
    "sNo": 128,
    "regalCode": "MA 128",
    "excellenceCode": "-",
    "varnCode": "-",
    "rcCode": "-",
    "snalcoCode": "-",
    "genericName": "Standing Seam Walkway Clamp 2",
    "imageFilename": "MA-128.png",
    "codeSource": "Regal",
    "priority": 1,
    "allCodes": "MA 128"
  },
  {
    "sNo": 129,
    "regalCode": "-",
    "excellenceCode": "-",
    "varnCode": "-",
    "rcCode": "-",
    "snalcoCode": "-",
    "genericName": "C45 Strut Base (for Magnelis Long Rail)",
    "imageFilename": "RL-49709.png",
    "codeSource": "Ralco",
    "priority": 8,
    "allCodes": "RL 49709"
  },
  {
    "sNo": 130,
    "regalCode": "-",
    "excellenceCode": "-",
    "varnCode": "-",
    "rcCode": "-",
    "snalcoCode": "-",
    "genericName": "C45 Strut Latch (for Magnelis Long Rail)",
    "imageFilename": "RL-49708.png",
    "codeSource": "Ralco",
    "priority": 8,
    "allCodes": "RL 49708"
  },
  {
    "sNo": 131,
    "regalCode": "-",
    "excellenceCode": "-",
    "varnCode": "-",
    "rcCode": "-",
    "snalcoCode": "-",
    "genericName": "45x30 - U Channel",
    "imageFilename": "RL-49710.png",
    "codeSource": "Ralco",
    "priority": 8,
    "allCodes": "RL 49710"
  },
  {
    "sNo": 132,
    "regalCode": "-",
    "excellenceCode": "-",
    "varnCode": "-",
    "rcCode": "SU 21",
    "snalcoCode": "-",
    "genericName": "C45 Rail Jointer (for Magnelis Long Rail)",
    "imageFilename": "SU-21.png",
    "codeSource": "RC",
    "priority": 4,
    "allCodes": "SU 21"
  },
  {
    "sNo": 133,
    "regalCode": "-",
    "excellenceCode": "-",
    "varnCode": "-",
    "rcCode": "-",
    "snalcoCode": "SN 5313",
    "genericName": "H Bracket for 100mm Box Column",
    "imageFilename": "SN-5313.png",
    "codeSource": "SNALCO",
    "priority": 5,
    "allCodes": "SN 5313"
  },
  {
    "sNo": 134,
    "regalCode": "-",
    "excellenceCode": "-",
    "varnCode": "-",
    "rcCode": "-",
    "snalcoCode": "SN 5314",
    "genericName": "100mm Box Column",
    "imageFilename": "SN-5314.png",
    "codeSource": "SNALCO",
    "priority": 5,
    "allCodes": "SN 5314"
  },
  {
    "sNo": 135,
    "regalCode": "-",
    "excellenceCode": "-",
    "varnCode": "-",
    "rcCode": "-",
    "snalcoCode": "SN 5317",
    "genericName": "5 Deg Elevator",
    "imageFilename": "SN-5317.png",
    "codeSource": "SNALCO",
    "priority": 5,
    "allCodes": "SN 5317"
  },
  {
    "sNo": 136,
    "regalCode": "-",
    "excellenceCode": "-",
    "varnCode": "-",
    "rcCode": "-",
    "snalcoCode": "SN 5318",
    "genericName": "120mm Short Rail",
    "imageFilename": "SN-5318.png",
    "codeSource": "SNALCO",
    "priority": 5,
    "allCodes": "SN 5318"
  },
  {
    "sNo": 137,
    "regalCode": "-",
    "excellenceCode": "-",
    "varnCode": "-",
    "rcCode": "-",
    "snalcoCode": "-",
    "genericName": "Strut Rail Nut",
    "imageFilename": "RL-49704.png",
    "codeSource": "Ralco",
    "priority": 8,
    "allCodes": "RL 49704"
  },
  {
    "sNo": 138,
    "regalCode": "-",
    "excellenceCode": "-",
    "varnCode": "-",
    "rcCode": "-",
    "snalcoCode": "-",
    "genericName": "150mm Short Rail",
    "imageFilename": "SR-02-(JM).png",
    "codeSource": "JM",
    "priority": 7,
    "allCodes": "SR 02 (JM)"
  },
  {
    "sNo": 139,
    "regalCode": "-",
    "excellenceCode": "-",
    "varnCode": "-",
    "rcCode": "-",
    "snalcoCode": "-",
    "genericName": "150mm Inter-Lock Column",
    "imageFilename": "DR-3.png",
    "codeSource": "Darshan",
    "priority": 6,
    "allCodes": "DR 3"
  },
  {
    "sNo": 140,
    "regalCode": "MA 129",
    "excellenceCode": "-",
    "varnCode": "-",
    "rcCode": "-",
    "snalcoCode": "-",
    "genericName": "100mm Part A - 2 Part Seam Clamp",
    "imageFilename": "MA-129.png",
    "codeSource": "Regal",
    "priority": 1,
    "allCodes": "MA 129"
  }
]